hfsapi/__init__.py
hfsapi/cli.py
hfsapi/cli_config.py
hfsapi/client.py
hfsapi/models.py
hfsapi-0.1.5.dist-info/METADATA
hfsapi-0.1.5.dist-info/WHEEL
hfsapi-0.1.5.dist-info/entry_points.txt
hfsapi-0.1.5.dist-info/top_level.txt
hfsapi-0.1.5.dist-info/RECORD
