Metadata-Version: 2.4
Name: hfsapi
Version: 0.1.5
Summary: HFS (HTTP File Server) Python API 客户端
Author: Multiple AI models (mixed)
Requires-Python: >=3.10
Requires-Dist: httpx>=0.27.0
Requires-Dist: typer>=0.12.0
Provides-Extra: dev
Requires-Dist: pytest>=7.0.0; extra == "dev"
